 {
    "category": "",
    "status": "pending",
    "identifier": "the-net-complete-tv-series",
    "title": "The Net",
    "desc": "Computer programmer Angela Bennett discovers a shadowy group of cyber terrorists who completely erase her true identity. Falsely labeled a criminal, she finds herself on the run, and she'll never stop until she's got her life back.",
    "start": "",
    "end": "",
    "imdb": "",
    "added": "2025-09-06T03:01:25.529Z",
    "lastmodified": "2025-09-06T03:01:25.529Z",
    "published": "",
    "approvedby": "",
    "playlist": ""
}